{
  "slide": 4,
  "width": 1920,
  "height": 1080,
  "duration": 31.56,
  "layers": [
    {
      "name": "slide_04_title_01.png",
      "type": "title",
      "x": 405,
      "y": 79,
      "width": 1063,
      "height": 63,
      "z_index": 5,
      "animation": "fade-in-down",
      "start": 0.45,
      "duration": 0.7,
      "narration_cue": "title"
    },
    {
      "name": "slide_04_arrow_01.png",
      "type": "arrow",
      "x": 84,
      "y": 82,
      "width": 206,
      "height": 56,
      "z_index": 6,
      "animation": "wipe-in",
      "start": 2.55,
      "duration": 0.7,
      "narration_cue": "arrow"
    },
    {
      "name": "slide_04_icon_01.png",
      "type": "icon",
      "x": 164,
      "y": 331,
      "width": 129,
      "height": 135,
      "z_index": 7,
      "animation": "pop-in",
      "start": 4.64,
      "duration": 0.7,
      "narration_cue": "icon"
    },
    {
      "name": "slide_04_icon_02.png",
      "type": "icon",
      "x": 472,
      "y": 331,
      "width": 107,
      "height": 135,
      "z_index": 8,
      "animation": "pop-in",
      "start": 6.74,
      "duration": 0.7,
      "narration_cue": "icon"
    },
    {
      "name": "slide_04_icon_03.png",
      "type": "icon",
      "x": 755,
      "y": 329,
      "width": 118,
      "height": 138,
      "z_index": 9,
      "animation": "pop-in",
      "start": 8.84,
      "duration": 0.7,
      "narration_cue": "icon"
    },
    {
      "name": "slide_04_icon_04.png",
      "type": "icon",
      "x": 1048,
      "y": 332,
      "width": 116,
      "height": 134,
      "z_index": 10,
      "animation": "pop-in",
      "start": 10.94,
      "duration": 0.7,
      "narration_cue": "icon"
    },
    {
      "name": "slide_04_icon_05.png",
      "type": "icon",
      "x": 1346,
      "y": 331,
      "width": 99,
      "height": 135,
      "z_index": 11,
      "animation": "pop-in",
      "start": 13.03,
      "duration": 0.7,
      "narration_cue": "icon"
    },
    {
      "name": "slide_04_icon_06.png",
      "type": "icon",
      "x": 1637,
      "y": 331,
      "width": 95,
      "height": 135,
      "z_index": 12,
      "animation": "pop-in",
      "start": 15.13,
      "duration": 0.7,
      "narration_cue": "icon"
    },
    {
      "name": "slide_04_illustration_01.png",
      "type": "illustration",
      "x": 113,
      "y": 529,
      "width": 530,
      "height": 200,
      "z_index": 13,
      "animation": "zoom-in",
      "start": 17.23,
      "duration": 0.7,
      "narration_cue": "illustration"
    },
    {
      "name": "slide_04_illustration_02.png",
      "type": "illustration",
      "x": 696,
      "y": 571,
      "width": 211,
      "height": 120,
      "z_index": 14,
      "animation": "zoom-in",
      "start": 19.32,
      "duration": 0.7,
      "narration_cue": "illustration"
    },
    {
      "name": "slide_04_illustration_03.png",
      "type": "illustration",
      "x": 985,
      "y": 532,
      "width": 221,
      "height": 159,
      "z_index": 15,
      "animation": "zoom-in",
      "start": 21.42,
      "duration": 0.7,
      "narration_cue": "illustration"
    },
    {
      "name": "slide_04_illustration_04.png",
      "type": "illustration",
      "x": 1275,
      "y": 531,
      "width": 242,
      "height": 160,
      "z_index": 16,
      "animation": "zoom-in",
      "start": 23.52,
      "duration": 0.7,
      "narration_cue": "illustration"
    },
    {
      "name": "slide_04_illustration_05.png",
      "type": "illustration",
      "x": 1566,
      "y": 531,
      "width": 243,
      "height": 160,
      "z_index": 17,
      "animation": "zoom-in",
      "start": 25.62,
      "duration": 0.7,
      "narration_cue": "illustration"
    },
    {
      "name": "slide_04_key_point_card_01.png",
      "type": "key_point_card",
      "x": 90,
      "y": 823,
      "width": 1740,
      "height": 160,
      "z_index": 18,
      "animation": "fade-in-up",
      "start": 27.71,
      "duration": 0.7,
      "narration_cue": "key_point_card"
    }
  ]
}